zarth_utils/__init__.py
zarth_utils/config.py
zarth_utils/drawer.py
zarth_utils/general_utils.py
zarth_utils/jupyter_utils.py
zarth_utils/logger.py
zarth_utils/nn_utils.py
zarth_utils/recorder.py
zarth_utils/text_processing.py
zarth_utils/timer.py
zarth_utils-1.3.dist-info/METADATA
zarth_utils-1.3.dist-info/WHEEL
zarth_utils-1.3.dist-info/top_level.txt
zarth_utils-1.3.dist-info/RECORD
