Metadata-Version: 2.2
Name: zarth_utils
Version: 1.3
Summary: Package used for my personal development on ML projects.
Requires-Python: >=3.7
Requires-Dist: matplotlib
Requires-Dist: tqdm
Requires-Dist: pandas
Requires-Dist: numpy
Requires-Dist: joblib
Requires-Dist: gitpython
Requires-Dist: ipython
Requires-Dist: wandb
Requires-Dist: scikit-learn
Requires-Dist: gitpython
Requires-Dist: ipython
Provides-Extra: all
Requires-Dist: nltk; extra == "all"
Requires-Dist: torch; extra == "all"
Requires-Dist: tensorflow; extra == "all"
Requires-Dist: jupyterlab; extra == "all"
Provides-Extra: hf
Requires-Dist: transformers; extra == "hf"
Requires-Dist: accelerate; extra == "hf"
Requires-Dist: trl; extra == "hf"
Requires-Dist: datasets; extra == "hf"
Requires-Dist: diffusers; extra == "hf"
Requires-Dist: tokenizers; extra == "hf"
Requires-Dist: huggingface_hub; extra == "hf"
